forker/Request.py
forker/WebSocketServer.py
forker/__init__.py
forker/__main__.py
forker/listen.py
forker-0.1.3.dist-info/LICENSE.txt
forker-0.1.3.dist-info/METADATA
forker-0.1.3.dist-info/WHEEL
forker-0.1.3.dist-info/top_level.txt
forker-0.1.3.dist-info/RECORD
