Metadata-Version: 2.1
Name: forker
Version: 0.1.3
Summary: A forking webserver and websocket server.
Home-page: https://github.com/darinmcgill/forker
Author: Darin McGill
Keywords: wsgi cgi websocket websockets forking http
Classifier: Development Status :: 4 - Beta
Classifier: Programming Language :: Python :: 2
Classifier: Programming Language :: Python :: 2.7
Classifier: Programming Language :: Python :: 3
Classifier: Programming Language :: Python :: 3.5
Classifier: Programming Language :: Python :: 3.6
License-File: LICENSE.txt
